phlasch/__init__.py
phlasch/__main__.py
phlasch/alembic.ini
phlasch/migrators.py
phlasch/runners.py
phlasch/utils.py
phlasch/db/__init__.py
phlasch/db/configure.py
phlasch/db/queries.py
phlasch/db/settings.py
phlasch/db/tables.py
phlasch/db/migrations/env.py
phlasch/db/migrations/script.py.mako
phlasch/db/migrations/versions/bfd35ebcbeb5_added_link_table.py
phlasch/redirector/__init__.py
phlasch/redirector/configure.py
phlasch/redirector/routers.py
phlasch/redirector/views.py
phlasch/redirector/swagger/redirect.yaml
phlasch/shortener/__init__.py
phlasch/shortener/configure.py
phlasch/shortener/routers.py
phlasch/shortener/settings.py
phlasch/shortener/utils.py
phlasch/shortener/validators.py
phlasch/shortener/views.py
phlasch/shortener/swagger/shorten.yaml
phlasch/stats/__init__.py
phlasch/stats/configure.py
phlasch/stats/routers.py
phlasch/stats/settings.py
phlasch/stats/views.py
phlasch/stats/swagger/stats_list.yaml
phlasch/stats/swagger/stats_retrieve.yaml
phlasch-1.0.2.dist-info/LICENSE
phlasch-1.0.2.dist-info/METADATA
phlasch-1.0.2.dist-info/WHEEL
phlasch-1.0.2.dist-info/top_level.txt
phlasch-1.0.2.dist-info/RECORD
