Metadata-Version: 2.1
Name: phlasch
Version: 1.0.2
Summary: A url shortener.
Home-page: https://github.com/bbmokhtari/phlasch
Author: Behzad B. Mokhtari
Author-email: behzad.public@gmail.com
License: UNKNOWN
Project-URL: Documentation, https://github.com/bbmokhtari/phlasch
Project-URL: Source, https://github.com/bbmokhtari/phlasch
Project-URL: Tracker, https://github.com/bbmokhtari/phlasch/issues
Keywords: url-shortener url-shortener-microservice
Platform: UNKNOWN
Classifier: Development Status :: 4 - Beta
Classifier: Environment :: Console
Classifier: Framework :: AsyncIO
Classifier: Intended Audience :: Developers
Classifier: Intended Audience :: Education
Classifier: Intended Audience :: Information Technology
Classifier: License :: OSI Approved :: MIT License
Classifier: Natural Language :: English
Classifier: Operating System :: OS Independent
Classifier: Programming Language :: Python :: 3.7
Classifier: Programming Language :: Python :: 3.8
Classifier: Programming Language :: Python :: 3.9
Classifier: Topic :: Internet
Requires-Python: >=3.7, <4
Requires-Dist: aiohttp[speedups]
Requires-Dist: aiohttp-swagger[performance]
Requires-Dist: aiopg[sa]
Requires-Dist: alembic
Requires-Dist: gunicorn
